siphashc.pyd
siphashc/__init__.pyi
siphashc/py.typed
siphashc-2.7.dist-info/licenses/LICENSE.md
siphashc-2.7.dist-info/METADATA
siphashc-2.7.dist-info/WHEEL
siphashc-2.7.dist-info/top_level.txt
siphashc-2.7.dist-info/zip-safe
siphashc-2.7.dist-info/RECORD
