Metadata-Version: 2.4
Name: siphashc
Version: 2.7
Summary: Python module (in c) for siphash-2-4
Author-email: Michal Čihař <michal@weblate.org>
License-Expression: ISC
Project-URL: Funding, https://weblate.org/donate/
Project-URL: Homepage, https://github.com/WeblateOrg/siphashc
Project-URL: Issue Tracker, https://github.com/WeblateOrg/siphashc/issues
Project-URL: Source Code, https://github.com/WeblateOrg/siphashc
Project-URL: Twitter, https://twitter.com/WeblateOrg
Keywords: siphash,siphash-2-4
Classifier: Development Status :: 5 - Production/Stable
Classifier: Intended Audience :: Developers
Classifier: Operating System :: OS Independent
Classifier: Programming Language :: Python
Classifier: Programming Language :: Python :: 3
Classifier: Programming Language :: Python :: 3.10
Classifier: Programming Language :: Python :: 3.11
Classifier: Programming Language :: Python :: 3.12
Classifier: Programming Language :: Python :: 3.13
Classifier: Programming Language :: Python :: 3.14
Classifier: Topic :: Software Development :: Libraries :: Python Modules
Requires-Python: >=3.10
License-File: LICENSE.md
Dynamic: license-file
